helloWorld/__init__.py
helloWorld/hello.py
Hello_World_Pini-1.0.0.dist-info/METADATA
Hello_World_Pini-1.0.0.dist-info/WHEEL
Hello_World_Pini-1.0.0.dist-info/top_level.txt
Hello_World_Pini-1.0.0.dist-info/RECORD
